pydantic_decoder/__init__.py
pydantic_decoder/__meta__.py
pydantic_decoder/decoder.py
pydantic_decoder/__pycache__/__init__.cpython-38.pyc
pydantic_decoder/__pycache__/__meta__.cpython-38.pyc
pydantic_decoder/__pycache__/decoder.cpython-38.pyc
pydantic_decoder-1.0.2.dist-info/LICENSE
pydantic_decoder-1.0.2.dist-info/METADATA
pydantic_decoder-1.0.2.dist-info/WHEEL
pydantic_decoder-1.0.2.dist-info/top_level.txt
pydantic_decoder-1.0.2.dist-info/RECORD
