Metadata-Version: 2.1
Name: pydantic-decoder
Version: 1.0.2
Summary: Convert json text back into proper Pydantic models.
Home-page: https://github.com/justengel/pydantic_decoder
Author: Justin Engel
Author-email: jtengel08@gmail.com
License: MIT
Download-URL: https://github.com/justengel/pydantic_decoder/archive/v1.0.2.tar.gz
Keywords: pydantic json decode encode
Platform: any
Classifier: Programming Language :: Python
Classifier: Programming Language :: Python :: 3
Classifier: Operating System :: OS Independent
Requires-Dist: pydantic (>=1.5.1)
